setup.cfg
setup.py
pycardfinder/__init__.py
pycardfinder/__main__.py
pycardfinder/scanner.py
pycardfinder.egg-info/PKG-INFO
pycardfinder.egg-info/SOURCES.txt
pycardfinder.egg-info/dependency_links.txt
pycardfinder.egg-info/requires.txt
pycardfinder.egg-info/top_level.txt